__init__.py
wiktionaryparser.py
tests/__init__.py
tests/context.py
tests/test.py
utils/__init__.py
utils/utils.py
wiktionaryparser_ml-0.0.1.data/data/readme/readme.md
wiktionaryparser_ml-0.0.1.data/data/requirements/requirements.txt
wiktionaryparser_ml-0.0.1.data/data/testOutput/testOutput.json
wiktionaryparser_ml-0.0.1.dist-info/LICENSE.txt
wiktionaryparser_ml-0.0.1.dist-info/METADATA
wiktionaryparser_ml-0.0.1.dist-info/WHEEL
wiktionaryparser_ml-0.0.1.dist-info/top_level.txt
wiktionaryparser_ml-0.0.1.dist-info/RECORD
