Metadata-Version: 2.1
Name: wiktionaryparser-ml
Version: 0.0.1
Summary: A tool to parse word data from wiktionary.com into a JSON object. Based on wiktionary parser by Suyash Behera
Home-page: https://github.com/Maxim75/WiktionaryParser
Author: Maksym Kozlenko
Author-email: max@kozlenko.info
License: UNKNOWN
Download-URL: https://github.com/Maxim75/WiktionaryParser/archive/master.zip
Keywords: Parser,Wiktionary
Platform: UNKNOWN
Classifier: Development Status :: 5 - Production/Stable
Classifier: License :: OSI Approved :: MIT License
Requires-Dist: beautifulsoup4
Requires-Dist: requests
